shownamer/__init__.py
shownamer/cli.py
shownamer-2.0.0.dist-info/licenses/LICENSE
shownamer-2.0.0.dist-info/METADATA
shownamer-2.0.0.dist-info/WHEEL
shownamer-2.0.0.dist-info/entry_points.txt
shownamer-2.0.0.dist-info/top_level.txt
shownamer-2.0.0.dist-info/RECORD
