Metadata-Version: 2.4
Name: shownamer
Version: 2.0.0
Summary: Rename TV show Media files with Respective episode Titles/Names.
Home-page: https://github.com/theamallalgi/shownamer
Author: Amal Lalgi
Classifier: Programming Language :: Python :: 3
Classifier: License :: OSI Approved :: MIT License
Classifier: Operating System :: OS Independent
Requires-Python: >=3.6
License-File: LICENSE
Requires-Dist: requests
Requires-Dist: guessit
Requires-Dist: IMDbPY
Dynamic: author
Dynamic: classifier
Dynamic: description
Dynamic: description-content-type
Dynamic: home-page
Dynamic: license-file
Dynamic: requires-dist
Dynamic: requires-python
Dynamic: summary
